pykingas/HardSphere.py
pykingas/KineticGas_r.cp310-win_amd64.pyd
pykingas/MieKinGas.py
pykingas/MieType.py
pykingas/PseudoHardSphere.py
pykingas/__init__.py
pykingas/__main__.py
pykingas/py_KineticGas.py
pykingas/fluids/AR.json
pykingas/fluids/C1.json
pykingas/fluids/C2.json
pykingas/fluids/C3.json
pykingas/fluids/CO2.json
pykingas/fluids/D2.json
pykingas/fluids/H2.json
pykingas/fluids/H2O.json
pykingas/fluids/HE.json
pykingas/fluids/KR.json
pykingas/fluids/LJF.json
pykingas/fluids/N2.json
pykingas/fluids/NC10.json
pykingas/fluids/NC15.json
pykingas/fluids/NC20.json
pykingas/fluids/NC22.json
pykingas/fluids/NC4.json
pykingas/fluids/NC5.json
pykingas/fluids/NC6.json
pykingas/fluids/NC7.json
pykingas/fluids/NC8.json
pykingas/fluids/NC9.json
pykingas/fluids/NE.json
pykingas/fluids/O-H2.json
pykingas/fluids/O2.json
pykingas/fluids/P-H2.json
pykingas/fluids/XE.json
pykingas-2.0.0.dist-info/LICENSE
pykingas-2.0.0.dist-info/METADATA
pykingas-2.0.0.dist-info/WHEEL
pykingas-2.0.0.dist-info/top_level.txt
pykingas-2.0.0.dist-info/RECORD
