Metadata-Version: 2.1
Name: pykingas
Version: 2.0.0
Summary: Revised Enskog theory for Mie fluids, and other spherical potentials. Allows prediction of transport coefficients such as diffusion coefficients, viscosities, thermal diffusion coefficients and thermal conductivities. In dense, multicomponent gas mixtures and supercritical mixtures.
Home-page: https://github.com/thermotools/KineticGas
Author: Vegard Gjeldvik Jervell
Author-email: vegard.g.j@icloud.com
License-File: LICENSE
Requires-Dist: numpy (~=1.22)
Requires-Dist: scipy (~=1.7)
Requires-Dist: thermopack (~=2.1)
